Workbook
Name StartingBalance: 'Summary NIS'!$K$2
Name StartingBalance: 'Summary USD'!$K$2

Sheet Summary NIS
B2: Budget | I2: Starting balance: | K2: 0
B4: Monthly Expenses: | C4: =D8 -> 4325 | D4: Monthly Income: | E4: =I8 -> 4115 | F4: Monthly What's Left: | G4: =SUM(E4-C4) -> -210
B5: Weekly Expenses: | C5: =C4/4 -> 1081.25 | D5: Weekly Income: | E5: =E4/4 -> 1028.75 | F5: Weekly What's Left: | G5: =G4/4 -> -52.5
B6: Expenses | G6: Income
D7: Monthly | E7: Weekly | I7: Monthly | J7: Weekly
B8: Total | D8: =sum(D9:D19) -> 4325 | E8: =sum(E9:E19) -> 1143.75 | G8: Total | I8: =sum(I9:I18) -> 4115 | J8: =sum(J9:J18) -> 1028.75
B10: Food | D10: 1200 | E10: =D10/4 -> 300 | G10: Allowance | I10: 1350 | J10: =I10/4 -> 337.5
B11: Health/medical | D11: 1300 | E11: =D11/4 -> 325 | G11: Paycheck | I11: 1000 | J11: =I11/4 -> 250
B12: Transportation | D12: 465 | E12: =D12/4 -> 116.25 | G12: Meds | I12: 1300 | J12: =I12/4 -> 325
B13: Toiletries | D13: 150 | E13: =D13/4 -> 37.5 | G13: Rav-Kav | I13: 465 | J13: =I13/4 -> 116.25
B14: Subscriptions | D14: 70 | E14: =D14/4 -> 17.5
B15: Vape | D15: 150 | E15: =D15/4 -> 37.5
B16: Off-Base Food | D16: 500 | E16: =D16/4 -> 125 | J16: =if(isblank($G16), "", sumif(Transactions!$J:$J,$G16,Transactions!$H:$H)) | K16: =if(isblank($G16), "", J16-I16)
B17: Hostel | D17: 240 | E17: =D17/4 -> 60 | J17: =if(isblank($G17), "", sumif(Transactions!$J:$J,$G17,Transactions!$H:$H)) | K17: =if(isblank($G17), "", J17-I17)
B18: Other | D18: 250 | E18: =D18/2 -> 125 | J18: =if(isblank($G18), "", sumif(Transactions!$J:$J,$G18,Transactions!$H:$H)) | K18: =if(isblank($G18), "", J18-I18)

Sheet Summary USD
B2: Budget | I2: Starting balance: | K2: 0
B4: Monthly Expenses: | C4: =D8 -> 1305 | D4: Monthly Income: | E4: =I8 -> 1232 | F4: Monthly What's Left: | G4: =SUM(E4-C4) -> -73
B5: Weekly Expenses: | C5: =C4/4 -> 326.25 | D5: Weekly Income: | E5: =E4/4 -> 308 | F5: Weekly What's Left: | G5: =G4/4 -> -18.25
B6: Expenses | G6: Income
D7: Monthly | E7: Weekly | I7: Monthly | J7: Weekly
B8: Total | D8: =sum(D9:D19) -> 1305 | E8: =sum(E9:E19) -> 345.25 | G8: Total | I8: =sum(I9:I18) -> 1232 | J8: =sum(J9:J18) -> 308
B10: Food | D10: 362 | E10: =D10/4 -> 90.5 | G10: Allowance | I10: 400 | J10: =I10/4 -> 100
B11: Health/medical | D11: 392 | E11: =D11/4 -> 98 | G11: Paycheck | I11: 300 | J11: =I11/4 -> 75
B12: Transportation | D12: 140 | E12: =D12/4 -> 35 | G12: Meds | I12: 392 | J12: =I12/4 -> 98
B13: Toiletries | D13: 45 | E13: =D13/4 -> 11.25 | G13: Rav-Kav | I13: 140 | J13: =I13/4 -> 35
B14: Subscriptions | D14: 22 | E14: =D14/4 -> 5.5
B15: Vape | D15: 45 | E15: =D15/4 -> 11.25
B16: Off-Base Food | D16: 150 | E16: =D16/4 -> 37.5 | J16: =if(isblank($G16), "", sumif(Transactions!$J:$J,$G16,Transactions!$H:$H)) | K16: =if(isblank($G16), "", J16-I16)
B17: Hostel | D17: 73 | E17: =D17/4 -> 18.25 | J17: =if(isblank($G17), "", sumif(Transactions!$J:$J,$G17,Transactions!$H:$H)) | K17: =if(isblank($G17), "", J17-I17)
B18: Other | D18: 76 | E18: =D18/2 -> 38 | J18: =if(isblank($G18), "", sumif(Transactions!$J:$J,$G18,Transactions!$H:$H)) | K18: =if(isblank($G18), "", J18-I18)
